README
setup.py
bin/mp3organiser
mp3organiser/__init__.py
mp3organiser/mp3organiser.py
mp3organiser.egg-info/PKG-INFO
mp3organiser.egg-info/SOURCES.txt
mp3organiser.egg-info/dependency_links.txt
mp3organiser.egg-info/requires.txt
mp3organiser.egg-info/top_level.txt
mp3organiser/test/__init__.py
mp3organiser/test/test_mp3organiser.py