Metadata-Version: 1.0
Name: mp3organiser
Version: 0.1
Summary: Organises and tags mp3 files and folders
Home-page: UNKNOWN
Author: Brendan Maguire
Author-email: maguire.brendan@gmail.com
License: MIT
Keywords: mp3 tag organise
Platform: UNKNOWN
